Metadata-Version: 1.0
Name: docx2html
Version: 0.2.1
Summary: docx (OOXML) to html converter
Home-page: http://github.com/PolicyStat/docx2html/
Author: Jason Ward
Author-email: jason.louard.ward@gmail.com
License: BSD
Platform: any
Classifier: Development Status :: 3 - Alpha
Classifier: Programming Language :: Python
Classifier: Intended Audience :: Developers
Classifier: License :: OSI Approved :: BSD License
Classifier: Operating System :: OS Independent
Classifier: Topic :: Text Processing :: Markup :: HTML
Classifier: Topic :: Text Processing :: Markup :: XML
